{
	"class" : {
		"forPath:" : "cmfcmf 7/30/2019 15:35",
		"on:" : "cf 5/11/2019 10:24" },
	"instance" : {
		"children" : "cf 5/11/2019 10:16",
		"delete" : "cf 5/13/2019 21:32",
		"extension" : "cf 5/11/2019 10:31",
		"fileEntry" : "cf 5/11/2019 10:16",
		"fileEntry:" : "cf 5/11/2019 10:16",
		"fullPath" : "ek 5/13/2019 17:29",
		"hasChildren" : "cf 5/11/2019 10:17",
		"lastModified" : "lp 7/7/2019 13:57",
		"name" : "cf 5/11/2019 10:17",
		"parent" : "fn 5/13/2020 12:05",
		"read" : "lp 7/7/2019 14:50",
		"readBinary" : "cmfcmf 6/23/2019 17:20",
		"rename:" : "cf 5/13/2019 22:17",
		"size" : "cf 5/11/2019 10:27",
		"write:" : "cf 5/11/2019 10:32" } }
