{
	"class" : {
		"asBoolean:" : "fn 3/5/2021 14:39",
		"asDate:" : "fn 12/12/2019 20:42",
		"asDouble:" : "fn 3/5/2021 14:41",
		"asDuration:" : "fn 12/12/2019 22:40",
		"asInstant:" : "fn 12/12/2019 22:54",
		"asLong:" : "fn 3/5/2021 14:41",
		"asPointer:" : "fn 3/9/2021 12:27",
		"asString:" : "fn 3/5/2021 14:42",
		"asTime:" : "fn 12/12/2019 20:42",
		"asTimeZone:" : "fn 12/12/2019 23:09",
		"execute:with:" : "fn 3/5/2021 14:47",
		"fitsInDouble:" : "fn 3/5/2021 14:41",
		"fitsInLong:" : "fn 3/5/2021 14:40",
		"getArraySize:" : "fn 3/5/2021 14:35",
		"getDeclaringMetaObject:" : "fn 3/5/2021 15:01",
		"getExceptionCause:" : "fn 11/12/2020 11:32",
		"getExceptionExitStatus:" : "fn 11/12/2020 10:48",
		"getExceptionMessage:" : "fn 11/12/2020 11:32",
		"getExceptionStackTrace:" : "fn 11/12/2020 11:33",
		"getExceptionType:" : "fn 11/12/2020 10:47",
		"getExecutableName:" : "fn 3/5/2021 14:47",
		"getLanguage:" : "fn 5/6/2020 14:48",
		"getLanguageInfo:" : "fn 1/26/2021 14:11",
		"getMemberSize:" : "fn 1/24/2020 14:49",
		"getMemberSize:includeInternal:" : "fn 1/24/2020 14:48",
		"getMembers:" : "fn 1/24/2020 14:50",
		"getMembers:includeInternal:" : "fn 3/5/2021 14:34",
		"getMetaObject:" : "fn 3/5/2021 14:48",
		"getMetaQualifiedName:" : "fn 3/5/2021 14:49",
		"getMetaSimpleName:" : "fn 3/5/2021 14:49",
		"getScopeParent:" : "fn 3/9/2021 14:58",
		"getSmalltalkScope" : "fn 11/12/2020 11:17",
		"getSourceLocation:" : "fn 7/12/2020 23:04",
		"hasArrayElements:" : "fn 3/5/2021 14:35",
		"hasDeclaringMetaObject:" : "fn 3/5/2021 15:02",
		"hasExceptionCause:" : "fn 3/5/2021 14:25",
		"hasExceptionMessage:" : "fn 3/5/2021 14:25",
		"hasExceptionStackTrace:" : "fn 3/5/2021 14:25",
		"hasExecutableName:" : "fn 3/5/2021 14:47",
		"hasIdentity:" : "fn 3/5/2021 14:25",
		"hasLanguage:" : "fn 3/5/2021 14:46",
		"hasMemberReadSideEffects:member:" : "fn 3/5/2021 14:26",
		"hasMemberWriteSideEffects:member:" : "fn 3/5/2021 14:26",
		"hasMembers:" : "fn 3/5/2021 14:33",
		"hasMetaObject:" : "fn 3/5/2021 14:43",
		"hasScopeParent:" : "fn 3/9/2021 14:57",
		"hasSourceLocation:" : "fn 3/5/2021 14:43",
		"hostIdentityHashCode:" : "fn 2/11/2021 12:04",
		"identityHashCode:" : "fn 9/3/2020 10:35",
		"instantiate:with:" : "fn 3/9/2021 12:40",
		"invokeMember:member:arguments:" : "fn 3/5/2021 14:56",
		"isArrayElementExisting:index:" : "fn 3/5/2021 14:44",
		"isArrayElementInsertable:index:" : "fn 3/5/2021 14:52",
		"isArrayElementModifiable:index:" : "fn 3/5/2021 14:52",
		"isArrayElementReadable:index:" : "fn 3/5/2021 14:51",
		"isArrayElementRemovable:index:" : "fn 3/5/2021 14:52",
		"isArrayElementWritable:index:" : "fn 3/5/2021 14:45",
		"isBoolean:" : "fn 3/5/2021 14:29",
		"isDate:" : "fn 3/5/2021 14:40",
		"isDuration:" : "fn 3/5/2021 14:40",
		"isException:" : "fn 3/5/2021 14:29",
		"isExceptionIncompleteSource:" : "fn 11/12/2020 11:37",
		"isExecutable:" : "fn 3/5/2021 14:30",
		"isHostFunction:" : "fn 3/5/2021 14:27",
		"isHostObject:" : "fn 3/5/2021 14:27",
		"isHostSymbol:" : "fn 3/5/2021 14:27",
		"isIdentical:to:" : "fn 3/5/2021 14:31",
		"isInstant:" : "fn 3/5/2021 14:28",
		"isInstantiable:" : "fn 3/5/2021 14:31",
		"isMemberExisting:member:" : "fn 3/5/2021 14:56",
		"isMemberInsertable:member:" : "fn 3/5/2021 14:32",
		"isMemberInternal:member:" : "fn 3/5/2021 14:32",
		"isMemberInvocable:member:" : "fn 3/5/2021 14:32",
		"isMemberModifiable:member:" : "fn 3/5/2021 14:32",
		"isMemberReadable:member:" : "fn 3/5/2021 14:53",
		"isMemberRemovable:member:" : "fn 3/5/2021 14:54",
		"isMemberWritable:member:" : "fn 3/5/2021 14:54",
		"isMetaInstance:instance:" : "fn 3/5/2021 15:03",
		"isMetaObject:" : "fn 3/5/2021 14:48",
		"isNull:" : "fn 3/5/2021 14:38",
		"isPointer:" : "fn 3/5/2021 14:27",
		"isScope:" : "fn 3/9/2021 14:57",
		"isString:" : "fn 3/5/2021 14:40",
		"isTime:" : "fn 3/5/2021 14:27",
		"isTimeZone:" : "fn 3/5/2021 14:27",
		"memberToSelector:for:" : "fn 3/9/2021 12:49",
		"memberToSelector:for:arguments:" : "fn 3/9/2021 12:49",
		"readArrayElement:index:" : "fn 3/5/2021 14:52",
		"readMember:member:" : "fn 3/5/2021 14:57",
		"removeArrayElement:index:" : "fn 12/3/2019 11:53",
		"removeMember:member:" : "fn 3/5/2021 14:58",
		"selectorToMember:" : "fn 3/9/2021 12:35",
		"throwException:" : "fn 12/12/2019 20:57",
		"toDisplayString:" : "fn 3/5/2021 15:15",
		"toDisplayString:allowSideEffects:" : "fn 3/5/2021 15:12",
		"writeArrayElement:index:value:" : "fn 3/5/2021 14:53",
		"writeMember:member:value:" : "fn 3/5/2021 14:59" },
	"instance" : {
		 } }
